_version.py
craftgate/__init__.py
craftgate/py.typed
craftgate/request_options.py
craftgate/adapter/__init__.py
craftgate/adapter/bank_account_tracking_adapter.py
craftgate/adapter/base_adapter.py
craftgate/adapter/bkm_express_payment_adapter.py
craftgate/adapter/file_reporting_adapter.py
craftgate/adapter/fraud_adapter.py
craftgate/adapter/hook_adapter.py
craftgate/adapter/installment_adapter.py
craftgate/adapter/juzdan_payment_adapter.py
craftgate/adapter/masterpass_payment_adapter.py
craftgate/adapter/merchant_adapter.py
craftgate/adapter/merchant_apm_adapter.py
craftgate/adapter/onboarding_adapter.py
craftgate/adapter/pay_by_link_adapter.py
craftgate/adapter/payment_adapter.py
craftgate/adapter/payment_reporting_adapter.py
craftgate/adapter/payment_token_adapter.py
craftgate/adapter/settlement_adapter.py
craftgate/adapter/settlement_reporting_adapter.py
craftgate/adapter/wallet_adapter.py
craftgate/exception/__init__.py
craftgate/exception/api_exception.py
craftgate/model/__init__.py
craftgate/model/account_owner.py
craftgate/model/additional_action.py
craftgate/model/apm_additional_action.py
craftgate/model/apm_type.py
craftgate/model/approval_status.py
craftgate/model/autopilot_state.py
craftgate/model/bank_account_tracking_source.py
craftgate/model/bnpl_cart_item_type.py
craftgate/model/bounce_status.py
craftgate/model/card_association.py
craftgate/model/card_brand.py
craftgate/model/card_expiry_status.py
craftgate/model/card_provider.py
craftgate/model/card_type.py
craftgate/model/currency.py
craftgate/model/file_status.py
craftgate/model/fraud_action.py
craftgate/model/fraud_check_status.py
craftgate/model/fraud_operation.py
craftgate/model/fraud_result.py
craftgate/model/fraud_value.py
craftgate/model/fraud_value_type.py
craftgate/model/loyalty.py
craftgate/model/loyalty_data.py
craftgate/model/loyalty_params.py
craftgate/model/loyalty_type.py
craftgate/model/masterpass_validation_type.py
craftgate/model/member_type.py
craftgate/model/merchant_type.py
craftgate-1.0.0.dist-info/licenses/LICENSE
craftgate-1.0.0.dist-info/METADATA
craftgate-1.0.0.dist-info/WHEEL
craftgate-1.0.0.dist-info/top_level.txt
craftgate-1.0.0.dist-info/RECORD
