Metadata-Version: 2.4
Name: craftgate
Version: 1.0.0
Summary: Python client for Craftgate API
Author-email: Craftgate <support@craftgate.io>
License: MIT License
Project-URL: Homepage, https://github.com/craftgate/craftgate-python-client
Project-URL: Documentation, https://developer.craftgate.io
Project-URL: Source, https://github.com/craftgate/craftgate-python-client
Project-URL: Issues, https://github.com/craftgate/craftgate-python-client/issues
Keywords: craftgate,payments,api,client,sdk
Classifier: Development Status :: 5 - Production/Stable
Classifier: Intended Audience :: Developers
Classifier: License :: OSI Approved :: MIT License
Classifier: Operating System :: OS Independent
Classifier: Programming Language :: Python :: 3
Classifier: Programming Language :: Python :: 3 :: Only
Classifier: Programming Language :: Python :: 3.6
Classifier: Programming Language :: Python :: 3.7
Classifier: Programming Language :: Python :: 3.8
Classifier: Programming Language :: Python :: 3.9
Classifier: Programming Language :: Python :: 3.10
Classifier: Programming Language :: Python :: 3.11
Classifier: Programming Language :: Python :: 3.12
Classifier: Programming Language :: Python :: Implementation :: PyPy
Classifier: Typing :: Typed
Classifier: Topic :: Software Development :: Libraries :: Python Modules
Requires-Python: >=3.6
License-File: LICENSE
Requires-Dist: requests>=2.20
Dynamic: license-file
